README.rst
setup.py
django_yunpian/__init__.py
django_yunpian/compat.py
django_yunpian.egg-info/PKG-INFO
django_yunpian.egg-info/SOURCES.txt
django_yunpian.egg-info/dependency_links.txt
django_yunpian.egg-info/requires.txt
django_yunpian.egg-info/top_level.txt