Metadata-Version: 1.0
Name: django-yunpian
Version: 0.0.1
Summary: Django extension for YunPian API
Home-page: https://github.com/hausir/django-yunpian
Author: hausir
Author-email: hausir@icloud.com
License: MIT
Platform: UNKNOWN
